vsmfdin/ED_offset.py
vsmfdin/MFDIN_arch.py
vsmfdin/__init__.py
vsmfdin/arch_util.py
vsmfdin/deform_conv.py
vsmfdin/models/MFDIN_old_2P.pth
vsmfdin-1.0.0.dist-info/METADATA
vsmfdin-1.0.0.dist-info/WHEEL
vsmfdin-1.0.0.dist-info/licenses/LICENSE
vsmfdin-1.0.0.dist-info/RECORD
