Metadata-Version: 2.3
Name: vsmfdin
Version: 1.0.0
Summary: MFDIN function for VapourSynth
Project-URL: Homepage, https://github.com/HolyWu/vs-mfdin
Project-URL: Issues, https://github.com/HolyWu/vs-mfdin/issues
Author-email: HolyWu <holywu@gmail.com>
Keywords: MFDIN,PyTorch,TensorRT,VapourSynth
Classifier: Environment :: GPU :: NVIDIA CUDA
Classifier: License :: OSI Approved :: MIT License
Classifier: Operating System :: OS Independent
Classifier: Programming Language :: Python :: 3
Classifier: Topic :: Multimedia :: Video
Requires-Python: >=3.10
Requires-Dist: numpy
Requires-Dist: torch>=2.5.1
Requires-Dist: vapoursynth>=66
